mlxserver/__init__.py
mlxserver/chat.py
mlxserver/delete.py
mlxserver/generate.py
mlxserver/list.py
mlxserver/load.py
mlxserver/pull.py
mlxserver/server.py
mlxserver/show.py
mlxserver/test.py
mlxserver-0.1.14.dist-info/LICENSE
mlxserver-0.1.14.dist-info/METADATA
mlxserver-0.1.14.dist-info/WHEEL
mlxserver-0.1.14.dist-info/top_level.txt
mlxserver-0.1.14.dist-info/RECORD
