Metadata-Version: 2.1
Name: mlxserver
Version: 0.1.14
Summary: Server for the MLX ML library.
Author-email: Mustafa Aljadery <aljadery@usc.edu>, Siddharth Sharma <sidshr@stanford.edu>
License: Copyright 2023 Mustafa Aljadery, Siddharth Sharma.
Project-URL: Homepage, https://www.mlxserver.com/
Project-URL: Repository, https://github.com/mustafaaljadery/mlx-server/
Classifier: Development Status :: 3 - Alpha
Classifier: Operating System :: OS Independent
Classifier: License :: OSI Approved :: MIT License
Classifier: Programming Language :: Python :: 3
Requires-Python: >=3.7
License-File: LICENSE
Requires-Dist: Flask
Requires-Dist: mlx
Requires-Dist: mlx-lm
Requires-Dist: flask-cors
Requires-Dist: huggingface-hub
